astropydantic/__init__.py
astropydantic/icrs.py
astropydantic/quantity.py
astropydantic/time.py
astropydantic/unit.py
astropydantic-0.0.5.dist-info/licenses/LICENSE
astropydantic-0.0.5.dist-info/METADATA
astropydantic-0.0.5.dist-info/WHEEL
astropydantic-0.0.5.dist-info/top_level.txt
astropydantic-0.0.5.dist-info/RECORD
