Metadata-Version: 2.4
Name: astropydantic
Version: 0.0.5
Author: Maximilian Linhoff
Author-email: Josh Borrow <josh@joshborrow.com>
Requires-Python: >=3.11
License-File: LICENSE
Requires-Dist: pydantic>2.0.0
Requires-Dist: astropy
Provides-Extra: dev
Requires-Dist: pytest; extra == "dev"
Requires-Dist: ruff; extra == "dev"
Requires-Dist: coverage; extra == "dev"
Requires-Dist: pytest-cov; extra == "dev"
Requires-Dist: pre-commit; extra == "dev"
Requires-Dist: fastapi; extra == "dev"
Requires-Dist: httpx; extra == "dev"
Dynamic: license-file
